df/__init__.py
df/code.py
df/codeclient.py
df/enums.py
df/exceptions.py
df/template.py
df/values.py
test/basic.py
test/codeclient_test.py
test/count.py
DiamondFire.py-0.0.5.dist-info/LICENSE
DiamondFire.py-0.0.5.dist-info/METADATA
DiamondFire.py-0.0.5.dist-info/WHEEL
DiamondFire.py-0.0.5.dist-info/top_level.txt
DiamondFire.py-0.0.5.dist-info/RECORD
