Metadata-Version: 2.2
Name: DiamondFire.py
Version: 0.0.5
Summary: DiamondFire templating library in Python.
Author: HellishBro
License: MIT License
Project-URL: Homepage, https://github.com/TechnicalDF/DiamondFire.py
Project-URL: Issues, https://github.com/TechnicalDF/DiamondFire.py/issues
Keywords: DiamondFire
Classifier: Programming Language :: Python :: 3.12
Classifier: License :: OSI Approved :: MIT License
Classifier: Operating System :: OS Independent
Requires-Python: >=3.12
License-File: LICENSE
Requires-Dist: amulet-nbt
Requires-Dist: websockets
Requires-Dist: setuptools
